supertape_gui/__init__.py
supertape_gui/main.py
supertape_gui/main_window.py
supertape_gui/resources/icons/app_icon.ico
supertape_gui/resources/icons/app_icon.svg
supertape_gui/resources/icons/app_icon_128.png
supertape_gui/resources/icons/app_icon_16.png
supertape_gui/resources/icons/app_icon_256.png
supertape_gui/resources/icons/app_icon_32.png
supertape_gui/resources/icons/app_icon_48.png
supertape_gui/resources/icons/app_icon_64.png
supertape_gui/resources/icons/tape_asm.svg
supertape_gui/resources/icons/tape_basic.svg
supertape_gui/resources/icons/tape_data.svg
supertape_gui/resources/icons/tape_machine.svg
supertape_gui/utils/__init__.py
supertape_gui/utils/audio_buffer.py
supertape_gui/utils/config_manager.py
supertape_gui/utils/file_compiler.py
supertape_gui/utils/formatters.py
supertape_gui/utils/pipeline_state.py
supertape_gui/widgets/__init__.py
supertape_gui/widgets/asm_type_dialog.py
supertape_gui/widgets/bits_view_widget.py
supertape_gui/widgets/block_indicator_widget.py
supertape_gui/widgets/editor_config_dialog.py
supertape_gui/widgets/hex_dump_widget.py
supertape_gui/widgets/tape_collection_widget.py
supertape_gui/widgets/tape_history_dialog.py
supertape_gui/widgets/tape_icon_widget.py
supertape_gui/widgets/tape_info_dialog.py
supertape_gui/widgets/waveform_widget.py
supertape_gui/workers/__init__.py
supertape_gui/workers/audio_player_worker.py
supertape_gui/workers/audio_worker.py
supertape_gui/workers/gui_listeners.py
supertape_gui-0.3.0.dev1.dist-info/METADATA
supertape_gui-0.3.0.dev1.dist-info/WHEEL
supertape_gui-0.3.0.dev1.dist-info/entry_points.txt
supertape_gui-0.3.0.dev1.dist-info/RECORD
