Metadata-Version: 2.4
Name: supertape-gui
Version: 0.3.0.dev1
Summary: Multi-platform GUI for supertape - duplex audio communication with vintage computers
License: LICENSE
Author: Yannick Kirschhoffer
Author-email: alcibiade@alcibiade.org
Requires-Python: >=3.11,<3.14
Classifier: License :: Other/Proprietary License
Classifier: Programming Language :: Python :: 3
Classifier: Programming Language :: Python :: 3.11
Classifier: Programming Language :: Python :: 3.12
Classifier: Programming Language :: Python :: 3.13
Requires-Dist: PySide6 (>=6.10.1,<7.0.0)
Requires-Dist: supertape (>=1.0.0.dev10,<2.0.0)
